pytsal/__init__.py
pytsal/anomaly.py
pytsal/dataset.py
pytsal/forecasting.py
pytsal/internal/__init__.py
pytsal/internal/entity.py
pytsal/internal/containers/__init__.py
pytsal/internal/containers/base_container.py
pytsal/internal/containers/metrics/__init__.py
pytsal/internal/containers/metrics/base_metric.py
pytsal/internal/containers/models/__init__.py
pytsal/internal/containers/models/base_model.py
pytsal/internal/containers/models/forecasting.py
pytsal/internal/utils/__init__.py
pytsal/internal/utils/data_loader.py
pytsal/internal/utils/helpers.py
pytsal/preprocessor/__init__.py
pytsal/visualization/__init__.py
pytsal/visualization/base_visualization.py
pytsal/visualization/eda.py
pytsal/visualization/validation.py
pytsal-1.1.1.dist-info/LICENSE
pytsal-1.1.1.dist-info/METADATA
pytsal-1.1.1.dist-info/WHEEL
pytsal-1.1.1.dist-info/top_level.txt
pytsal-1.1.1.dist-info/RECORD
