Metadata-Version: 2.1
Name: pytsal
Version: 1.1.1
Summary: An easy to use open-source python framework for Time Series analysis, visualization and forecasting along with AutoTS
Home-page: https://github.com/KrishnanSG/pytsal
Author: Krishnan S G
Author-email: krishsg525@gmail.com
License: UNKNOWN
Keywords: time,series,analysis,tsa,visualization,autots,datascience
Platform: UNKNOWN
Classifier: Programming Language :: Python :: 3
Classifier: License :: OSI Approved :: GNU General Public License v3 (GPLv3)
Classifier: Operating System :: OS Independent
Classifier: Operating System :: OS Independent
Classifier: Topic :: Software Development :: Libraries :: Python Modules
Classifier: Topic :: Software Development :: Libraries
Classifier: Topic :: Software Development
Classifier: Intended Audience :: Developers
Classifier: Programming Language :: Python :: 3 :: Only
Classifier: Programming Language :: Python :: 3.6
Classifier: Programming Language :: Python :: 3.7
Classifier: Programming Language :: Python :: 3.8
Requires-Python: >=3.6
Requires-Dist: pandas (~=1.2.4)
Requires-Dist: statsmodels (~=0.12.2)
Requires-Dist: matplotlib (~=3.4.1)
Requires-Dist: seaborn (~=0.11.1)
